doc/source/conf.py
doc/source/images/favicon.py
doc/source/images/hero.py
arch-7.2.0.dist-info/top_level.txt
arch-7.2.0.dist-info/RECORD
arch-7.2.0.dist-info/LICENSE.md
arch-7.2.0.dist-info/METADATA
arch-7.2.0.dist-info/WHEEL
ci/performance.py
arch/typing.py
arch/conftest.py
arch/__init__.py
arch/_version.py
arch/py.typed
arch/__future__/reindexing.py
arch/__future__/__init__.py
arch/data/__init__.py
arch/data/utility.py
arch/data/binary/binary.csv.gz
arch/data/binary/__init__.py
arch/data/sp500/sp500.csv.gz
arch/data/sp500/__init__.py
arch/data/crude/__init__.py
arch/data/crude/crude.csv.gz
arch/data/nasdaq/__init__.py
arch/data/nasdaq/nasdaq.csv.gz
arch/data/wti/__init__.py
arch/data/wti/wti.csv.gz
arch/data/core_cpi/__init__.py
arch/data/core_cpi/core-cpi.csv.gz
arch/data/default/default.csv.gz
arch/data/default/__init__.py
arch/data/vix/vix.csv.gz
arch/data/vix/__init__.py
arch/data/frenchdata/frenchdata.csv.gz
arch/data/frenchdata/__init__.py
arch/compat/statsmodels.py
arch/compat/numba.py
arch/compat/__init__.py
arch/compat/pandas.py
arch/tests/__init__.py
arch/tests/test_tester.py
arch/tests/test_compat.py
arch/tests/test_examples.py
arch/tests/test_data.py
arch/tests/covariance/__init__.py
arch/tests/covariance/test_covariance.py
arch/tests/unitroot/test_unitroot.py
arch/tests/unitroot/test_fmols_ccr.py
arch/tests/unitroot/__init__.py
arch/tests/unitroot/test_dynamic_ols.py
arch/tests/unitroot/test_phillips_ouliaris.py
arch/tests/unitroot/test_engle_granger.py
arch/tests/unitroot/cointegration_data.py
arch/tests/unitroot/data/__init__.py
arch/tests/unitroot/data/zivot-andrews.csv
arch/tests/bootstrap/__init__.py
arch/tests/bootstrap/test_multiple_comparison.py
arch/tests/bootstrap/test_block_length.py
arch/tests/bootstrap/test_bootstrap.py
arch/tests/univariate/test_distribution.py
arch/tests/univariate/test_recursions.py
arch/tests/univariate/test_arch_in_mean.py
arch/tests/univariate/test_volatility.py
arch/tests/univariate/__init__.py
arch/tests/univariate/test_rescale.py
arch/tests/univariate/test_moment.py
