Metadata-Version: 2.1
Name: arch
Version: 7.2.0
Summary: ARCH for Python
Author-email: Kevin Sheppard <kevin.k.sheppard@gmail.com>
Maintainer-email: Kevin Sheppard <kevin.k.sheppard@gmail.com>
License: # License
Project-URL: homepage, https://github.com/bashtage/arch
Project-URL: documentation, https://bashtage.github.io/arch/
Project-URL: repository, https://github.com/bashtage/arch
Project-URL: changelog, https://bashtage.github.io/arch/changes.html
Keywords: arch,ARCH,variance,econometrics,volatility,finance,GARCH,bootstrap,random walk,unit root,Dickey Fuller,time series,confidence intervals,multiple comparisons,Reality Check,SPA,StepM
Classifier: Development Status :: 5 - Production/Stable
Classifier: Intended Audience :: End Users/Desktop
Classifier: Intended Audience :: Financial and Insurance Industry
Classifier: Programming Language :: Python :: 3.9
Classifier: Programming Language :: Python :: 3.10
Classifier: Programming Language :: Python :: 3.11
Classifier: Programming Language :: Python :: 3.12
Classifier: License :: OSI Approved :: University of Illinois/NCSA Open Source License
Classifier: Operating System :: MacOS :: MacOS X
Classifier: Operating System :: Microsoft :: Windows
Classifier: Operating System :: POSIX
Classifier: Programming Language :: Python
Classifier: Programming Language :: Cython
Classifier: Topic :: Scientific/Engineering
Requires-Python: >=3.9
License-File: LICENSE.md
Requires-Dist: numpy>=1.22.3
Requires-Dist: scipy>=1.8
Requires-Dist: pandas>=1.4
Requires-Dist: statsmodels>=0.12
